[
  {
    "question": "¿Qué comando SQL se usa para eliminar una vista?",
    "options": ["DROP VIEW", "DELETE VIEW", "REMOVE VIEW", "TRUNCATE VIEW"],
    "answer": 0,
    "explanation": "DROP VIEW elimina una vista previamente creada en la base de datos."
  },
  {
    "question": "¿Qué comando SQL se usa para modificar una vista existente?",
    "options": ["ALTER VIEW", "UPDATE VIEW", "MODIFY VIEW", "CHANGE VIEW"],
    "answer": 0,
    "explanation": "ALTER VIEW permite redefinir la consulta que compone una vista existente."
  },
  {
    "question": "¿Qué tipo de objeto almacena una consulta reutilizable que devuelve un valor?",
    "options": ["Procedimiento almacenado", "Función", "Trigger", "Vista"],
    "answer": 1,
    "explanation": "Una función es un objeto que encapsula una consulta y devuelve un valor específico."
  },
  {
    "question": "¿Qué tipo de objeto ejecuta acciones automáticamente ante eventos como INSERT o DELETE?",
    "options": ["Vista", "Función", "Trigger", "Índice"],
    "answer": 2,
    "explanation": "Un trigger se activa automáticamente ante eventos definidos en una tabla, como inserciones o eliminaciones."
  },
  {
    "question": "¿Qué comando SQL se usa para crear un procedimiento almacenado?",
    "options": ["CREATE PROCEDURE", "DEFINE PROCEDURE", "MAKE PROCEDURE", "SET PROCEDURE"],
    "answer": 0,
    "explanation": "CREATE PROCEDURE define un bloque de código que puede ejecutarse repetidamente en la base de datos."
  },
  {
    "question": "¿Qué comando SQL se usa para ejecutar un procedimiento almacenado?",
    "options": ["EXEC", "CALL", "RUN", "PERFORM"],
    "answer": 1,
    "explanation": "CALL invoca un procedimiento almacenado en sistemas como MySQL; otros motores usan EXEC."
  },
  {
    "question": "¿Qué comando SQL se usa para eliminar un procedimiento almacenado?",
    "options": ["DROP PROCEDURE", "DELETE PROCEDURE", "REMOVE PROCEDURE", "TRUNCATE PROCEDURE"],
    "answer": 0,
    "explanation": "DROP PROCEDURE elimina un procedimiento almacenado de la base de datos."
  },
  {
    "question": "¿Qué comando SQL se usa para crear una función?",
    "options": ["CREATE FUNCTION", "DEFINE FUNCTION", "MAKE FUNCTION", "SET FUNCTION"],
    "answer": 0,
    "explanation": "CREATE FUNCTION define una función que puede devolver un valor y ser usada en consultas."
  },
  {
    "question": "¿Qué comando SQL se usa para eliminar una función?",
    "options": ["DROP FUNCTION", "DELETE FUNCTION", "REMOVE FUNCTION", "TRUNCATE FUNCTION"],
    "answer": 0,
    "explanation": "DROP FUNCTION elimina una función definida en la base de datos."
  },
  {
    "question": "¿Qué comando SQL se usa para crear un trigger?",
    "options": ["CREATE TRIGGER", "DEFINE TRIGGER", "MAKE TRIGGER", "SET TRIGGER"],
    "answer": 0,
    "explanation": "CREATE TRIGGER define una acción automática que se ejecuta ante eventos como INSERT o DELETE."
  },
  {
    "question": "¿Qué comando SQL se usa para eliminar un trigger?",
    "options": ["DROP TRIGGER", "DELETE TRIGGER", "REMOVE TRIGGER", "TRUNCATE TRIGGER"],
    "answer": 0,
    "explanation": "DROP TRIGGER elimina un trigger previamente definido en la base de datos."
  },
  {
    "question": "¿Qué técnica permite controlar el acceso a objetos de la base de datos?",
    "options": ["Indexación", "Normalización", "Gestión de privilegios", "Replicación"],
    "answer": 2,
    "explanation": "La gestión de privilegios permite definir qué usuarios pueden acceder o modificar objetos específicos."
  },
  {
    "question": "¿Qué comando SQL se usa para ver los privilegios de un usuario?",
    "options": ["SHOW GRANTS", "LIST PRIVILEGES", "DISPLAY PERMISSIONS", "VIEW RIGHTS"],
    "answer": 0,
    "explanation": "SHOW GRANTS muestra los privilegios asignados a un usuario en la base de datos."
  },
  {
    "question": "¿Qué técnica permite auditar el acceso y uso de la base de datos?",
    "options": ["Triggers", "Logs", "Views", "Functions"],
    "answer": 1,
    "explanation": "Los logs registran eventos como accesos, modificaciones y errores para fines de auditoría."
  },
  {
    "question": "¿Qué técnica permite mejorar el rendimiento de consultas frecuentes?",
    "options": ["Triggers", "Views", "Indexación", "Funciones"],
    "answer": 2,
    "explanation": "La indexación acelera el acceso a datos mediante estructuras que optimizan búsquedas."
  },
  {
    "question": "¿Qué tipo de índice se actualiza automáticamente al modificar datos?",
    "options": ["Índice estático", "Índice dinámico", "Índice automático", "Índice persistente"],
    "answer": 1,
    "explanation": "Los índices dinámicos se actualizan automáticamente cuando se insertan, modifican o eliminan datos."
  },
  {
    "question": "¿Qué técnica permite restaurar una base de datos a un estado anterior?",
    "options": ["Rollback", "Restore", "Undo", "Revert"],
    "answer": 1,
    "explanation": "Restore recupera una base de datos desde una copia de seguridad previa."
  },
  {
    "question": "¿Qué comando SQL se usa para revertir una transacción activa?",
    "options": ["ROLLBACK", "UNDO", "REVERT", "CANCEL"],
    "answer": 0,
    "explanation": "ROLLBACK revierte todos los cambios realizados en la transacción actual."
  },
  {
    "question": "¿Qué propiedad de las transacciones asegura que se ejecuten completamente o no se ejecuten en absoluto?",
    "options": ["Atomicidad", "Consistencia", "Aislamiento", "Durabilidad"],
    "answer": 0,
    "explanation": "La atomicidad garantiza que una transacción se ejecute completamente o se revierta por completo."
  },
  {
    "question": "¿Qué propiedad de las transacciones evita interferencias entre transacciones concurrentes?",
    "options": ["Atomicidad", "Consistencia", "Aislamiento", "Durabilidad"],
    "answer": 2,
    "explanation": "El aislamiento evita que transacciones concurrentes afecten sus resultados mutuamente."
  }
]
